HW2/F74046242/SRC/Controller.v
// Controller
module Controller ( opcode,
					funct,
					// write your code in here
					//mux
					RegDst,
					ra,
					ALUSrc,
					lh,
					sh,
					MemToReg,
					Jal,
					//DM
					DM_enable,
					//Regfile
					RegWrite,
					//ALU
					ALUOp,
					//JumpCtrl
					JControl
					);

		input  [5:0] opcode;
    input  [5:0] funct;

		// write your code in here

		//mux
		output reg RegDst;
		output reg ra;
		output reg ALUSrc;
		output reg lh;
		output reg sh;
		output reg MemToReg;
		output reg Jal;
		//output
		output reg [3:0] ALUOp;
		output reg [2:0] JControl;
		output reg RegWrite;
		output reg DM_enable;

		always @(opcode or funct) begin
			if(opcode == 6'b000000) begin
				ra <= 0;
				RegWrite <= 0;
				Jal <= 0;
				JControl <= 6;  //normal
				case (funct)
					//R-format
					6'b100000:  //add
					begin
						RegDst <= 1;
						ALUSrc <= 1;
						MemToReg <= 0;
						RegWrite <= 1;
						ALUOp <= 2;
						DM_enable <= 0;
					end
					6'b100010:  //sub
					begin
						RegDst <= 1;
						ALUSrc <= 1;
						MemToReg <= 0;
						RegWrite <= 1;
						ALUOp <= 6;
						DM_enable <= 0;
					end
					6'b100100:  //and
					begin
						RegDst <= 1;
						ALUSrc <= 1;
						MemToReg <= 0;
						RegWrite <= 1;
						ALUOp <= 0;
						DM_enable <= 0;
					end
					6'b100101:  //or
					begin
						RegDst <= 1;
						ALUSrc <= 1;
						MemToReg <= 0;
						RegWrite <= 1;
						ALUOp <= 1;
						DM_enable <= 0;
					end
					6'b100110:  //xor
					begin
						RegDst <= 1;
						ALUSrc <= 1;
						MemToReg <= 0;
						RegWrite <= 1;
						ALUOp <= 10;
						DM_enable <= 0;
					end
					6'b100111:  //nor
					begin
						RegDst <= 1;
						ALUSrc <= 1;
						MemToReg <= 0;
						RegWrite <= 1;
						ALUOp <= 9;
						DM_enable <= 0;
					end
					6'b101010:  //slt
					begin
						RegDst <= 1;
						ALUSrc <= 1;
						MemToReg <= 0;
						RegWrite <= 1;
						ALUOp <= 7;
						DM_enable <= 0;
					end
					6'b000000:  //sll
					begin
						RegDst <= 1;
						ALUSrc <= 1;
						MemToReg <= 0;
						RegWrite <= 1;
						ALUOp <= 11;
						DM_enable <= 0;
					end
					6'b000010:  //srl
					begin
						RegDst <= 1;
						ALUSrc <= 1;
						MemToReg <= 0;
						RegWrite <= 1;
						ALUOp <= 12;
						DM_enable <= 0;
					end
					6'b001000:  //jr
					begin
						ra <= 0;
						Jal <= 0;
						RegWrite <= 0;
						JControl <= 0;
					end
					6'b001001:  //jalr
					begin
						ra <= 1;
						Jal <= 1;
						RegWrite <= 1;
						JControl <= 1;
					end
					default:;
				endcase
			end
			else begin
				Jal <= 0;
				JControl <= 6;  //normal
				RegWrite <= 0;
				ra <= 0;
				case (opcode)
					//I-format
					6'b001000:  //addi
					begin
						RegDst <= 0;
						ALUSrc <= 0;
						MemToReg <= 0;
						RegWrite <= 1;
						ALUOp <= 2;
						DM_enable <= 0;
					end
					6'b001100:  //andi
					begin
						RegDst <= 0;
						ALUSrc <= 0;
						MemToReg <= 0;
						RegWrite <= 1;
						ALUOp <= 0;
						DM_enable <= 0;
					end
					6'b001010:  //slti
					begin
						RegDst <= 0;
						ALUSrc <= 0;
						MemToReg <= 0;
						RegWrite <= 1;
						ALUOp <= 7;
						DM_enable <= 0;
					end
					6'b000100:  //beq
					begin
						ALUSrc <= 1;
						RegWrite <= 0;
						ALUOp <= 13;
						DM_enable <= 0;
						ra <= 0;
						Jal <= 0;
						JControl <= 2;
					end
					6'b000101:  //bne
					begin
						ALUSrc <= 1;
						RegWrite <= 0;
						ALUOp <= 13;
						DM_enable <= 0;
						ra <= 0;
						Jal <= 0;
						JControl <= 3;
					end
					6'b100011:  //lw
					begin
						RegDst <= 0;
						ALUSrc <= 0;
						MemToReg <= 1;
						RegWrite <= 1;
						ALUOp <= 2;
						lh <= 0;
						DM_enable <= 0;
						Jal <= 0;
					end
					6'b100001:  //lh
					begin
						RegDst <= 0;
						ALUSrc <= 0;
						MemToReg <= 1;
						RegWrite <= 1;
						ALUOp <= 2;
						lh <= 1;
						DM_enable <= 0;
						Jal <= 0;
					end
					6'b101011:  //sw
					begin
						ALUSrc <= 0;
						RegWrite <= 0;
						ALUOp <= 2;
						DM_enable <= 1;
						sh <= 0;
					end
					6'b101001:  //sh
					begin
						ALUSrc <= 0;
						RegWrite <= 0;
						ALUOp <= 2;
						DM_enable <= 1;
						sh <= 1;
					end
					//J-format
					6'b000010:  //j
					begin
						ra <= 0;
						Jal <= 0;
						RegWrite <= 0;
						JControl <= 4;
					end
					6'b000011:  //jal
					begin
						ra <= 1;
						Jal <= 1;
						RegWrite <= 1;
						JControl <= 5;
					end
					default:;
				endcase
			end
		end
endmodule

HW3/F74046242/SRC/ALU.v
// ALU

module ALU ( ALUOp,
			 src1,
			 src2,
			 shamt,
			 ALU_result,
			 Zero);
	
	parameter bit_size = 32;
	
	input [3:0] ALUOp;
	input [bit_size-1:0] src1;
	input [bit_size-1:0] src2;
	input [4:0] shamt;
	
	output reg[bit_size-1:0] ALU_result;
	output Zero;
	
	assign Zero = (ALU_result == 0);
	// write your code in here
	always @(ALUOp or src1 or src2) begin
		case (ALUOp)
			4'd0: ALU_result <= src1 & src2;            //and
			4'd1: ALU_result <= src1 | src2;            //or
			4'd2: ALU_result <= src1 + src2;            //add
			4'd6: ALU_result <= src1 - src2;            //sub
			4'd7: ALU_result <= (src1 - src2) >> 31;    //slt
			4'd9: ALU_result <= ~(src1 | src2);         //nor
			4'd10: ALU_result <= src1 ^ src2;           //xor
			4'd11: ALU_result <= src2 << shamt;         //sll
			4'd12: ALU_result <= src2 >> shamt;         //srl
			4'd13: ALU_result <= (src1 == src2);        //equal
			default: ALU_result <= 0;
		endcase
	end
endmodule

HW2/F74046242/SRC/Jump_Ctrl.v
// Jump_Ctrl

module Jump_Ctrl( Zero,
                  JumpOP,
				  // write your code in here
				  JControl
				  );

  input Zero;
	output reg [1:0] JumpOP;
	// write your code in here
	input [2:0] JControl;
	
	always @(*) begin
		case (JControl)
			3'd0: JumpOP <= 2;  //jr
			3'd1: JumpOP <= 2;  //jalr
			3'd2:  //beq
			begin 
				if(Zero == 0) begin
					JumpOP <= 1;
				end
				else begin
					JumpOP <= 0;
				end
			end  
			3'd3:  //bne
			begin
			 	if(Zero != 0) begin
			 		JumpOP <= 1;
			 	end
			 	else begin
			 		JumpOP <= 0;
			 	end
			end
			3'd4: JumpOP <= 3;  //j
			3'd5: JumpOP <= 3;  //jal
			default: JumpOP <= 0;
		endcase
	end

endmodule

HW2/F74046242/SRC/Regfile.v
// Regfile

module Regfile ( clk,
				 rst,
				 Read_addr_1,
				 Read_addr_2,
				 Read_data_1,
         Read_data_2,
				 RegWrite,
				 Write_addr,
				 Write_data);

	parameter bit_size = 32;

	input  clk, rst;
	input  [4:0] Read_addr_1;
	input  [4:0] Read_addr_2;

	output [bit_size-1:0] Read_data_1;  //RS
	output [bit_size-1:0] Read_data_2;  //RT

	input  RegWrite;
	input  [4:0] Write_addr;
	input  [bit_size-1:0] Write_data;

  // write your code in here
  
  reg [bit_size-1:0] reg_data [0:bit_size-1];
  integer i;

  assign Read_data_1 = reg_data[Read_addr_1];
  assign Read_data_2 = reg_data[Read_addr_2];
  always @(posedge clk or posedge rst) begin
  	if (rst) begin
  		// reset
  		for(i=0;i<bit_size;i=i+1)
  			reg_data[i] <= 0;
  	end
  	else if (RegWrite) begin
  		reg_data[Write_addr] <= Write_data;
  	end
  end
endmodule

HW2/F74046242/SRC/PC.v
// Program Counter

module PC ( clk,
			rst,
			PCin,
			PCout);
	
	parameter bit_size = 18;

	input  clk, rst;
	input  [bit_size-1:0] PCin;
	output reg [bit_size-1:0] PCout;

	// write your code in here

	always @(posedge clk or posedge rst) begin
		if (rst) begin
			// reset
			PCout <= 0;
		end
		else begin
			PCout <= PCin;
		end
	end

endmodule

HW2/F74046242/SRC/top.v
// top

module top ( 
			 clk,
       rst,
			 // Instruction Memory
			 IM_Address,
       Instruction,
			 // Data Memory
			 DM_Address,
			 DM_enable,
			 DM_Write_Data,
			 DM_Read_Data);

	parameter data_size = 32;
	parameter mem_size = 16;

	input  clk, rst;

	// Instruction Memory
	output [mem_size-1:0] IM_Address;
	input  [data_size-1:0] Instruction;

	// Data Memory
	output [mem_size-1:0] DM_Address;
	output DM_enable;
	output [data_size-1:0] DM_Write_Data;
  input  [data_size-1:0] DM_Read_Data;

	// write your code here

	wire [17:0] pcout;
	reg [17:0] pcin;
	wire [17:0] add1;
	wire [data_size-1:0] add2;
	wire [data_size-1:0] rs;
	wire [data_size-1:0] rt;

	wire RegDst,ra,ALUSrc,lh,sh,MemToReg,Jal;

	wire [4:0] RtRd;
	wire [4:0] WR;

	wire [15:0] imm;
	wire [data_size-1:0] immSignExten;
	wire [data_size-1:0] RorI;
	wire [data_size-1:0] regWD;


	wire regWrite,Zero;

	wire [3:0] ALUOp;
	wire [data_size-1:0] ALU_result;

	wire [data_size-1:0] lworlh;
	wire [data_size-1:0] sworsh;
	wire [data_size-1:0] toreg;


	wire [2:0] JControl;
	wire [1:0] JumpOP;

	PC pc(.clk(clk),.rst(rst),
			.PCin(pcin),
			.PCout(pcout));

	assign IM_Address = pcout[17:2];
	assign add1 = pcout + 4;

	assign add2 = add1 + 4;

	assign imm = Instruction[15:0];
	assign immSignExten = (imm[15])?({16'hffff,imm}):({16'h0000,imm});

	assign DM_Address = ALU_result[17:2];
	assign DM_Write_Data = sworsh;



	Regfile regfile(.clk(clk),.rst(rst),
			.Read_addr_1(Instruction[25:21]),
			.Read_addr_2(Instruction[20:16]),
			.Read_data_1(rs),
      .Read_data_2(rt),
			.RegWrite(regWrite),
			.Write_addr(WR),
			.Write_data(regWD));

	Jump_Ctrl jump_ctrl(.Zero(Zero),.JumpOP(JumpOP),.JControl(JControl));

	ALU alu(
			.ALUOp(ALUOp),
			.src1(rs),
			.src2(RorI),
			.shamt(Instruction[10:6]),
			.ALU_result(ALU_result),
			.Zero(Zero));


	Controller controller(
			.opcode(Instruction[31:26]),
			.funct(Instruction[5:0]),
			//mux
			.RegDst(RegDst),
			.ra(ra),
			.ALUSrc(ALUSrc),
			.lh(lh),
			.sh(sh),
			.MemToReg(MemToReg),
			.Jal(Jal),
			//DM
			.DM_enable(DM_enable),
			//Regfile
			.RegWrite(regWrite),
			//ALU
			.ALUOp(ALUOp),
			//JumpCtrl
			.JControl(JControl));

	//mux
	assign RtRd = (RegDst)?(Instruction[15:11]):(Instruction[20:16]);
	assign WR = (ra)?(5'd31):(RtRd);
	assign RorI = (ALUSrc)?(rt):(immSignExten);
	assign sworsh = (sh)?((rt[15])?({16'hffff,rt[15:0]}):({16'h0000,rt[15:0]})):(rt);
	assign lworlh = (lh)?((DM_Read_Data[15])?({16'hffff,DM_Read_Data[15:0]}):({16'h0000,DM_Read_Data[15:0]})):(DM_Read_Data);
	assign toreg = (MemToReg)?(lworlh):(ALU_result);
	assign regWD = (Jal)?(add2):(toreg);


	//mux of jctrl
	always @(*) begin
		case (JumpOP)
			0: pcin <= add1;
			1: pcin <= add1 + (imm << 2);
			2: pcin <= rs[17:0];
			3: pcin <= (imm << 2);
		endcase
	end
endmodule

HW2/F74046242/SRC/DM.v
// Data Memory

module DM (	clk,
			rst,
			DM_Address,
			DM_enable,
			DM_Write_Data,
			DM_Read_Data);

	parameter bit_size = 32;
	parameter mem_size = 16;

	input  clk, rst;
	input  [mem_size-1:0] DM_Address;
	input  DM_enable;
	input  [bit_size-1:0] DM_Write_Data;

	output [bit_size-1:0] DM_Read_Data;

	reg [bit_size-1:0] DM_data [0:( 2**mem_size-1 )];

	assign DM_Read_Data = DM_data[DM_Address];

	integer i;

	always @ (posedge clk or posedge rst) begin
		if (rst)
			for (i=0;i<2**mem_size;i=i+1)
				DM_data[i] <= 0;
		else if (DM_enable)
			DM_data[DM_Address] <= DM_Write_Data;
	end

endmodule

HW2/F74046242/SRC/IM.v
// Instruction Memory

module IM (	clk,
			rst,
			IM_Address,
			Instruction);

	parameter bit_size = 32;
	parameter mem_size = 16;

	input  clk, rst;
	input  [mem_size-1:0] IM_Address;

	output [bit_size-1:0] Instruction;

	reg [bit_size-1:0] IM_data [0:( 2**mem_size-1 )];

	assign Instruction = IM_data[IM_Address];

endmodule

HW2/F74046242/SRC/testfixture1.v
`timescale 1ns/10ps

`define TEST_DATA "./tb1/IM_data.dat"
`define golden_DM_DATA "./tb1/golden_DM.dat"
`define PERIOD 10
`define NUM_CLK 1000

module testfixture1;
	
parameter bit_size = 32;
parameter mem_size = 16;

reg clk, rst;
reg [31:0] golden_DM [0:99];
reg err_R, err_I, err_J;


// Instruction Memory
wire [mem_size-1:0] IM_Address;	
wire [bit_size-1:0] Instruction;

// Data Memory
wire [mem_size-1:0] DM_Address;
wire DM_enable;
wire [bit_size-1:0] DM_Write_Data;
wire [bit_size-1:0] DM_Read_Data;

IM IM1 (
.clk(clk),
.rst(rst),
.IM_Address(IM_Address),
.Instruction(Instruction)
);

DM DM1 ( 
.clk(clk),
.rst(rst),
.DM_Address(DM_Address),
.DM_enable(DM_enable),
.DM_Write_Data(DM_Write_Data),
.DM_Read_Data(DM_Read_Data)
);

top top1 (
.clk(clk),
.rst(rst),
// Instruction Memory
.IM_Address(IM_Address),
.Instruction(Instruction),
// Data Memory
.DM_Address(DM_Address),
.DM_enable(DM_enable),
.DM_Write_Data(DM_Write_Data),
.DM_Read_Data(DM_Read_Data)
);

// clk part
always #(`PERIOD/2) clk = ~clk;

integer i;

// to long
initial begin 
  #(`PERIOD * `NUM_CLK)
  $display("================================================================================================================");
  $display("--------------------------- (/`n`)/ ~#  There was something wrong with your code !! ---------------------------"); 
  $display("------------------ The simulation can't finished!!, Please check Branch, Jtype or jr is work or not !!! -------"); 
  $display("================================================================================================================");
  $finish;
end

// Check
initial begin

  // Check Rtype
  $display("[ testfuxture1.v ] Rtype test START !!");
  wait(IM_Address==31);
  for (i=0;i<10;i=i+1) begin
    if(golden_DM[i] != DM1.DM_data[i]) begin
	  $display("DM_data[%d] = %h  ERROR, EXPECT DM_data[%d]= %h ", i, DM1.DM_data[i], i, golden_DM[i]);
	  err_R = 1;
	end
  end
  if (err_R) begin			
	$display("============================================================================================");
	$display("\n (T_T)  The Rtype result of DM_data is FAIL(include addi)!!! there have some errors in all.\n");
	$display("============================================================================================");
	$finish;
  end
  else begin
	$display("============================================================================");
	$display("\n \\(^o^)/  The Rtype result of DM_data is PASS!!!\n");
	$display("============================================================================");		
  end
  
  // Check Itype
  $display("[ testfuxture1.v ] Itype test START !!");
  wait(IM_Address==42);
  for (i=10;i<15;i=i+1) begin
    if(golden_DM[i] != DM1.DM_data[i]) begin
      $display("DM_data[%d] = %h  ERROR, EXPECT DM_data[%d]= %h ", i, DM1.DM_data[i], i, golden_DM[i]);
      err_I = 1;
    end
  end
  if (err_I) begin		
    $display("============================================================================================");
    $display("\n (T_T)  The Itype result of DM_data is FAIL!!! there have some errors in all.\n");
    $display("============================================================================================");
    $finish;
  end
  else begin
    $display("============================================================================");
    $display("\n \\(^o^)/  The Itype result of DM_data is PASS!!!\n");
    $display("============================================================================");		
  end
  
  // Check Jtype
  $display("[ testfuxture1.v ] Jtype test START !!");
  wait(IM_Address==44);
  #(`PERIOD * 2) if(IM_Address < 51) begin
    err_J = 1;
  end
  #(`PERIOD * 4) if(IM_Address > 54) begin
    err_J = 1;
  end
  if (err_J) begin		
    $display("============================================================================================");
    $display("\n (T_T) The Jtype or Jr result of DM_data is FAIL!!! there have some errors in all.\n");
    $display("============================================================================================");
    $finish;
  end
  wait(IM_Address==60);
  $display("============================================================================");
  $display("\n \\(^o^)/  The Jtype result of DM_data is PASS!!!\n");
  $display("============================================================================");
  $display("\n");
  $display("        Single Cycle CPU				            ");
  $display("        ****************************              ");
  $display("        **                        **       /|__/|");
  $display("        **  Congratulations !!    **      / O,O  |");
  $display("        **                        **    /_____   |");
  $display("        **  Simulation PASS!!     **   /^ ^ ^ \\  |");
  $display("        **                        **  |^ ^ ^ ^ |w|");
  $display("        *************** ************   \\m___m__|_|");
  $display("         student ID :  F74046242                   "); 
  $display("\n");
  $finish;
end

// Reset
initial begin
  clk = 0;
  rst = 0;
  err_R = 0;
  err_I = 0;
  err_J = 0;
  $readmemh(`TEST_DATA, IM1.IM_data);
  $readmemh(`golden_DM_DATA, golden_DM);
  #6 rst = 1;
  #(`PERIOD ) rst = 0;
end

`ifdef VCD
initial begin
  $dumpfile("top.vcd");
  $dumpvars;
end
`endif
	
	
endmodule

HW2/F74046242/SRC/top.vcd
$date
	Wed Apr 26 16:35:11 2017
$end
$version
	Icarus Verilog
$end
$timescale
	10ps
$end
$scope module testfixture1 $end
$var wire 16 ! DM_Address [15:0] $end
$var wire 32 " DM_Read_Data [31:0] $end
$var wire 32 # DM_Write_Data [31:0] $end
$var wire 1 $ DM_enable $end
$var wire 16 % IM_Address [15:0] $end
$var wire 32 & Instruction [31:0] $end
$var reg 1 ' clk $end
$var reg 1 ( err_I $end
$var reg 1 ) err_J $end
$var reg 1 * err_R $end
$var integer 32 + i [31:0] $end
$var reg 1 , rst $end
$scope module IM1 $end
$var wire 16 - IM_Address [15:0] $end
$var wire 32 . Instruction [31:0] $end
$var wire 1 / clk $end
$var wire 1 0 rst $end
$upscope $end
$scope module DM1 $end
$var wire 16 1 DM_Address [15:0] $end
$var wire 32 2 DM_Read_Data [31:0] $end
$var wire 32 3 DM_Write_Data [31:0] $end
$var wire 1 $ DM_enable $end
$var wire 1 / clk $end
$var wire 1 0 rst $end
$var integer 32 4 i [31:0] $end
$upscope $end
$scope module top1 $end
$var wire 4 5 ALUOp [3:0] $end
$var wire 1 6 ALUSrc $end
$var wire 32 7 ALU_result [31:0] $end
$var wire 16 8 DM_Address [15:0] $end
$var wire 32 9 DM_Read_Data [31:0] $end
$var wire 32 : DM_Write_Data [31:0] $end
$var wire 1 $ DM_enable $end
$var wire 16 ; IM_Address [15:0] $end
$var wire 32 < Instruction [31:0] $end
$var wire 3 = JControl [2:0] $end
$var wire 1 > Jal $end
$var wire 2 ? JumpOP [1:0] $end
$var wire 1 @ MemToReg $end
$var wire 1 A RegDst $end
$var wire 32 B RorI [31:0] $end
$var wire 5 C RtRd [4:0] $end
$var wire 5 D WR [4:0] $end
$var wire 1 E Zero $end
$var wire 18 F add1 [17:0] $end
$var wire 32 G add2 [31:0] $end
$var wire 1 / clk $end
$var wire 16 H imm [15:0] $end
$var wire 32 I immSignExten [31:0] $end
$var wire 1 J lh $end
$var wire 32 K lworlh [31:0] $end
$var wire 18 L pcout [17:0] $end
$var wire 1 M ra $end
$var wire 32 N regWD [31:0] $end
$var wire 1 O regWrite $end
$var wire 32 P rs [31:0] $end
$var wire 1 0 rst $end
$var wire 32 Q rt [31:0] $end
$var wire 1 R sh $end
$var wire 32 S sworsh [31:0] $end
$var wire 32 T toreg [31:0] $end
$var reg 18 U pcin [17:0] $end
$scope module pc $end
$var wire 18 V PCin [17:0] $end
$var wire 1 / clk $end
$var wire 1 0 rst $end
$var reg 18 W PCout [17:0] $end
$upscope $end
$scope module regfile $end
$var wire 5 X Read_addr_1 [4:0] $end
$var wire 5 Y Read_addr_2 [4:0] $end
$var wire 32 Z Read_data_1 [31:0] $end
$var wire 32 [ Read_data_2 [31:0] $end
$var wire 1 O RegWrite $end
$var wire 5 \ Write_addr [4:0] $end
$var wire 32 ] Write_data [31:0] $end
$var wire 1 / clk $end
$var wire 1 0 rst $end
$var integer 32 ^ i [31:0] $end
$upscope $end
$scope module jump_ctrl $end
$var wire 3 _ JControl [2:0] $end
$var wire 1 E Zero $end
$var reg 2 ` JumpOP [1:0] $end
$upscope $end
$scope module alu $end
$var wire 4 a ALUOp [3:0] $end
$var wire 1 E Zero $end
$var wire 5 b shamt [4:0] $end
$var wire 32 c src1 [31:0] $end
$var wire 32 d src2 [31:0] $end
$var reg 32 e ALU_result [31:0] $end
$upscope $end
$scope module controller $end
$var wire 6 f funct [5:0] $end
$var wire 6 g opcode [5:0] $end
$var reg 4 h ALUOp [3:0] $end
$var reg 1 i ALUSrc $end
$var reg 1 j DM_enable $end
$var reg 3 k JControl [2:0] $end
$var reg 1 l Jal $end
$var reg 1 m MemToReg $end
$var reg 1 n RegDst $end
$var reg 1 o RegWrite $end
$var reg 1 p lh $end
$var reg 1 q ra $end
$var reg 1 r sh $end
$upscope $end
$upscope $end
$upscope $end
$enddefinitions $end
#0
$dumpvars
xr
0q
xp
0o
xn
xm
0l
b110 k
xj
xi
bx h
bx g
bx f
b0 e
bx d
bx c
bx b
bx a
b0 `
b110 _
bx ^
bx ]
bx \
bx [
bx Z
bx Y
bx X
bx W
bx V
bx U
bx T
bx S
xR
bx Q
bx P
0O
bx N
0M
bx L
bx K
xJ
bx I
bx H
bx G
bx F
1E
bx D
bx C
bx B
xA
x@
b0 ?
0>
b110 =
bx <
bx ;
bx :
bx 9
b0 8
b0 7
x6
bx 5
bx 4
bx 3
bx 2
b0 1
00
0/
bx .
bx -
0,
bx +
0*
0)
0(
0'
bx &
bx %
x$
bx #
bx "
b0 !
$end
#500
1'
1/
#600
0j
0$
b1011 h
b1011 5
b1011 a
1o
1O
0m
0@
1i
16
1n
1A
b100 U
b100 V
b0 S
b0 #
b0 3
b0 :
b0 N
b0 ]
b0 B
b0 d
b0 D
b0 \
b0 T
b0 I
b0 C
b0 K
b1000 G
b0 H
b0 X
b0 P
b0 Z
b0 c
b0 Y
b0 Q
b0 [
b0 b
b0 g
b0 f
b100 F
b0 &
b0 .
b0 <
b0 %
b0 -
b0 ;
b0 W
b0 L
b0 "
b0 2
b0 9
b100000 ^
b10000000000000000 4
1,
10
#1000
0'
0/
#1500
b10000000000000000 4
b100000 ^
1'
1/
#1600
0,
00
#2000
0'
0/
#2500
b1000 U
b1000 V
b1100 G
b1000 F
b1 %
b1 -
b1 ;
b100 W
b100 L
1'
1/
#3000
0'
0/
#3500
b1100 U
b1100 V
b10000 G
b1100 F
b10 %
b10 -
b10 ;
b1000 W
b1000 L
1'
1/
#4000
0'
0/
#4500
b10000 U
b10000 V
b10100 G
b10000 F
b11 %
b11 -
b11 ;
b1100 W
b1100 L
1'
1/
#5000
0'
0/
#5500
b10100 U
b10100 V
b11000 G
b10100 F
b100 %
b100 -
b100 ;
b10000 W
b10000 L
1'
1/
#6000
0'
0/
#6500
b11000 U
b11000 V
b11100 G
b11000 F
b101 %
b101 -
b101 ;
b10100 W
b10100 L
1'
1/
#7000
0'
0/
#7500
b11100 U
b11100 V
b100000 G
b11100 F
b110 %
b110 -
b110 ;
b11000 W
b11000 L
1'
1/
#8000
0'
0/
#8500
b100000 U
b100000 V
b100100 G
b100000 F
b111 %
b111 -
b111 ;
b11100 W
b11100 L
1'
1/
#9000
0'
0/
#9500
b100100 U
b100100 V
b101000 G
b100100 F
b1000 %
b1000 -
b1000 ;
b100000 W
b100000 L
1'
1/
#10000
0'
0/
#10500
b1000000000000 N
b1000000000000 ]
b1000000000000 T
b10000000000 !
b10000000000 1
b10000000000 8
b1000000000000 e
0E
b1000000000000 7
b1000000000000 B
b1000000000000 d
b10 h
b10 5
b10 a
0i
06
0n
0A
1o
1O
b101000 U
b101000 V
b100 D
b100 \
b1000000000000 I
b100 C
b101100 G
b1000000000000 H
b100 Y
b1000 g
b101000 F
b100000000001000001000000000000 &
b100000000001000001000000000000 .
b100000000001000001000000000000 <
b1001 %
b1001 -
b1001 ;
b100100 W
b100100 L
1'
1/
#11000
0'
0/
#11500
b10000000000000000000000000000 N
b10000000000000000000000000000 ]
b10000000000000000000000000000 T
b0 !
b0 1
b0 8
b10000000000000000000000000000 e
b10000000000000000000000000000 7
b1011 h
b1011 5
b1011 a
1i
16
1n
1A
1o
1O
b101100 U
b101100 V
b1000000000000 B
b1000000000000 d
b10010000000000 I
b110000 G
b10010000000000 H
b10000 b
b0 g
b101100 F
b1000010010000000000 &
b1000010010000000000 .
b1000010010000000000 <
b1010 %
b1010 -
b1010 ;
b1000000000000 S
b1000000000000 #
b1000000000000 3
b1000000000000 :
b101000 W
b101000 L
b1000000000000 Q
b1000000000000 [
1'
1/
#12000
0'
0/
#12500
b100 !
b100 1
b100 8
b10000 N
b10000 ]
b10000 T
b10000 e
0E
b10000 7
b10 h
b10 5
b10 a
0i
06
0n
0A
1o
1O
b110000 U
b110000 V
b10000 D
b10000 \
b10000 I
b10000 C
b110100 G
b10000 H
b10000 Y
b0 b
b1000 g
b10000 f
b0 S
b0 #
b0 3
b0 :
b10000 B
b10000 d
b110000 F
b100000000100000000000000010000 &
b100000000100000000000000010000 .
b100000000100000000000000010000 <
b1011 %
b1011 -
b1011 ;
b0 Q
b0 [
b101100 W
b101100 L
1'
1/
#13000
0'
0/
#13500
b10000000000000000000000000000 N
b10000000000000000000000000000 ]
b0 !
b0 1
b0 8
b10000000000000000000000000000 T
b10000000000000000000000000000 e
b10000000000000000000000000000 7
0r
0R
1j
1$
0o
0O
b110100 U
b110100 V
b0 B
b0 d
b0 I
b111000 G
b0 H
b100 X
b10000000000000000000000000000 P
b10000000000000000000000000000 Z
b10000000000000000000000000000 c
b101011 g
b0 f
b110100 F
b10101100100100000000000000000000 &
b10101100100100000000000000000000 .
b10101100100100000000000000000000 <
b1100 %
b1100 -
b1100 ;
b10000 S
b10000 #
b10000 3
b10000 :
b110000 W
b110000 L
b10000 Q
b10000 [
1'
1/
#14000
0'
0/
#14500
b11111 N
b11111 ]
b111 !
b111 1
b111 8
b11111 T
b11111 e
0E
b11111 7
0j
0$
1o
1O
b111000 U
b111000 V
b11111 B
b11111 d
b10001 D
b10001 \
b11111 I
b0 S
b0 #
b0 3
b0 :
b10001 C
b111100 G
b11111 H
b0 X
b0 P
b0 Z
b0 c
b10001 Y
b0 Q
b0 [
b1000 g
b11111 f
b111000 F
b100000000100010000000000011111 &
b100000000100010000000000011111 .
b100000000100010000000000011111 <
b1101 %
b1101 -
b1101 ;
b0 K
b110100 W
b110100 L
b0 "
b0 2
b0 9
1'
1/
#15000
0'
0/
#15500
b10000000000000000000000000100 N
b10000000000000000000000000100 ]
b1 !
b1 1
b1 8
b10000000000000000000000000100 T
b10000000000000000000000000100 e
b10000000000000000000000000100 7
1j
1$
0o
0O
b111100 U
b111100 V
b100 B
b100 d
b100 I
b1000000 G
b100 H
b100 X
b10000000000000000000000000000 P
b10000000000000000000000000000 Z
b10000000000000000000000000000 c
b101011 g
b100 f
b111100 F
b10101100100100010000000000000100 &
b10101100100100010000000000000100 .
b10101100100100010000000000000100 <
b1110 %
b1110 -
b1110 ;
b11111 S
b11111 #
b11111 3
b11111 :
b111000 W
b111000 L
b11111 Q
b11111 [
1'
1/
#16000
0'
0/
#16500
b101111 N
b101111 ]
b10010 D
b10010 \
b101111 T
b1011 !
b1011 1
b1011 8
b10010 C
b101111 e
b101111 7
0j
0$
1o
1O
1i
16
1n
1A
b1000000 U
b1000000 V
b11111 B
b11111 d
b11111111111111111001000000100000 I
b1000100 G
b1001000000100000 H
b10000 X
b10000 P
b10000 Z
b10000 c
b0 g
b100000 f
b1000000 F
b10000100011001000000100000 &
b10000100011001000000100000 .
b10000100011001000000100000 <
b1111 %
b1111 -
b1111 ;
b0 K
b111100 W
b111100 L
b0 "
b0 2
b0 9
1'
1/
#17000
0'
0/
#17500
b10 !
b10 1
b10 8
b10000000000000000000000001000 N
b10000000000000000000000001000 ]
b10000000000000000000000001000 T
b10000000000000000000000001000 e
b10000000000000000000000001000 7
1j
1$
0i
06
0o
0O
b1000100 U
b1000100 V
b0 D
b0 \
b1000 I
b101111 S
b101111 #
b101111 3
b101111 :
b1000 B
b1000 d
b0 C
b1001000 G
b1000 H
b100 X
b10000000000000000000000000000 P
b10000000000000000000000000000 Z
b10000000000000000000000000000 c
b10010 Y
b101111 Q
b101111 [
b101011 g
b1000 f
b1000100 F
b10101100100100100000000000001000 &
b10101100100100100000000000001000 .
b10101100100100100000000000001000 <
b10000 %
b10000 -
b10000 ;
b1000000 W
b1000000 L
1'
1/
#18000
0'
0/
#18500
b10000 N
b10000 ]
b10000 T
b100 !
b100 1
b100 8
b10000 e
b10000 7
0j
0$
b110 h
b110 5
b110 a
1o
1O
1i
16
b1001000 U
b1001000 V
b11111 B
b11111 d
b10011 D
b10011 \
b11111111111111111001100000100010 I
b11111 S
b11111 #
b11111 3
b11111 :
b10011 C
b1001100 G
b1001100000100010 H
b10010 X
b101111 P
b101111 Z
b101111 c
b10001 Y
b11111 Q
b11111 [
b0 g
b100010 f
b1001000 F
b10010100011001100000100010 &
b10010100011001100000100010 .
b10010100011001100000100010 <
b10001 %
b10001 -
b10001 ;
b0 K
b1000100 W
b1000100 L
b0 "
b0 2
b0 9
1'
1/
#19000
0'
0/
#19500
b10000000000000000000000001100 N
b10000000000000000000000001100 ]
b10000000000000000000000001100 T
b11 !
b11 1
b11 8
b10000000000000000000000001100 e
b10000000000000000000000001100 7
1j
1$
b10 h
b10 5
b10 a
0i
06
0o
0O
b1001100 U
b1001100 V
b0 D
b0 \
b1100 I
b10000 S
b10000 #
b10000 3
b10000 :
b1100 B
b1100 d
b0 C
b1010000 G
b1100 H
b100 X
b10000000000000000000000000000 P
b10000000000000000000000000000 Z
b10000000000000000000000000000 c
b10011 Y
b10000 Q
b10000 [
b101011 g
b1100 f
b1001100 F
b10101100100100110000000000001100 &
b10101100100100110000000000001100 .
b10101100100100110000000000001100 <
b10010 %
b10010 -
b10010 ;
b1001000 W
b1001000 L
1'
1/
#20000
0'
0/
